protclust/__init__.py
protclust/clustering.py
protclust/logger.py
protclust/preprocessing.py
protclust/splitting.py
protclust/utils.py
protclust-0.2.0.dist-info/licenses/LICENSE
protclust-0.2.0.dist-info/METADATA
protclust-0.2.0.dist-info/WHEEL
protclust-0.2.0.dist-info/top_level.txt
protclust-0.2.0.dist-info/RECORD
