Metadata-Version: 2.4
Name: protclust
Version: 0.2.0
Summary: Python tools for protein sequence clustering and dataset splitting
Author: Michael Scutari
License: MIT
Project-URL: Homepage, https://github.com/michaelscutari/protclust
Project-URL: Bug Tracker, https://github.com/michaelscutari/protclust/issues
Project-URL: Documentation, https://github.com/michaelscutari/protclust
Keywords: bioinformatics,protein,clustering,machine learning
Classifier: Programming Language :: Python :: 3
Classifier: License :: OSI Approved :: MIT License
Classifier: Operating System :: OS Independent
Classifier: Topic :: Scientific/Engineering :: Bio-Informatics
Classifier: Intended Audience :: Science/Research
Classifier: Development Status :: 4 - Beta
Requires-Python: >=3.7
License-File: LICENSE
Requires-Dist: numpy>=1.20.0
Requires-Dist: pandas>=1.5.0
Requires-Dist: scikit-learn>=1.0.0
Requires-Dist: pulp>=2.0.0
Dynamic: license-file
